tno/quantum/ml/classifiers/vc/__init__.py
tno/quantum/ml/classifiers/vc/_variational_classifier.py
tno/quantum/ml/classifiers/vc/py.typed
tno/quantum/ml/classifiers/vc/models/__init__.py
tno/quantum/ml/classifiers/vc/models/_base.py
tno/quantum/ml/classifiers/vc/models/expected_value_model.py
tno/quantum/ml/classifiers/vc/models/probability_model.py
tno/quantum/ml/classifiers/vc/test/__init__.py
tno/quantum/ml/classifiers/vc/test/test_parity_model.py
tno/quantum/ml/classifiers/vc/test/test_variational_classifier.py
tno_quantum_ml_classifiers_vc-3.0.1.dist-info/licenses/LICENSE
tno_quantum_ml_classifiers_vc-3.0.1.dist-info/METADATA
tno_quantum_ml_classifiers_vc-3.0.1.dist-info/WHEEL
tno_quantum_ml_classifiers_vc-3.0.1.dist-info/top_level.txt
tno_quantum_ml_classifiers_vc-3.0.1.dist-info/RECORD
