Metadata-Version: 2.4
Name: tno.quantum.ml.classifiers.vc
Version: 3.0.1
Summary: Quantum VC module
Author-email: TNO Quantum Code Lab <tnoquantum@tno.nl>
Maintainer-email: TNO Quantum Code Lab <tnoquantum@tno.nl>
License: Apache License, Version 2.0
Project-URL: Homepage, https://github.com/TNO-Quantum/
Project-URL: Documentation, https://tno-quantum.github.io/documentation/
Project-URL: Source, https://github.com/TNO-Quantum/ml.classifiers.vc
Keywords: TNO,Quantum
Platform: any
Classifier: License :: OSI Approved :: Apache Software License
Classifier: Programming Language :: Python :: 3
Classifier: Programming Language :: Python :: 3.9
Classifier: Programming Language :: Python :: 3.10
Classifier: Programming Language :: Python :: 3.11
Classifier: Programming Language :: Python :: 3.12
Classifier: Programming Language :: Python :: 3.13
Classifier: Operating System :: OS Independent
Classifier: Intended Audience :: Developers
Classifier: Intended Audience :: Information Technology
Classifier: Intended Audience :: Science/Research
Classifier: Typing :: Typed
Requires-Python: >=3.9
License-File: LICENSE
Requires-Dist: tno.quantum.utils~=5.1
Requires-Dist: scikit-learn~=1.6
Requires-Dist: numpy
Requires-Dist: pennylane
Requires-Dist: torch
Requires-Dist: torchtyping
Requires-Dist: tqdm
Requires-Dist: networkx<=3.2.1; python_version == "3.9"
Provides-Extra: tests
Requires-Dist: pytest>=8.1.1; extra == "tests"
Requires-Dist: pytest-cov>=4.1.0; extra == "tests"
Requires-Dist: tomlkit; extra == "tests"
Requires-Dist: pandas; extra == "tests"
Requires-Dist: tno.quantum.ml.datasets; extra == "tests"
Requires-Dist: pennylane-qiskit>=0.41; python_version < "3.13" and extra == "tests"
Dynamic: license-file
